{
    "501.Stairs": ["Corridor 1", "Corridor 4"],
    "502.Stairs": ["Corridor 1"],
    "510.Stairs": ["Corridor 2"],
    "516.Stairs": ["521"],
    "Lift 1": ["Main entrance", "Corridor 3"],
    "Lift 2": ["Corridor 4"],

    "Corridor 1": ["501.Stairs", "502.Stairs", "Examination Cell", "Main entrance", "501", "502A", "502B", "502C"],
    "Corridor 2": ["510.Stairs", "503", "505A", "505B", "506A", "506B", "507A", "507B", "508"],
    "Corridor 3": ["HOD cabin", "511A", "511B", "512", "513A", "513B", "514", "515", "516A", "516B", "517", "518", "519", "520", "Lift 1"],
    "Corridor 4": ["501.Stairs", "Corridor 3", "Lift 2", "521", "522", "523", "524", "525", "526", "527"],

    "Main entrance": ["Lift 1", "Corridor 1"],
    "Examination Cell": ["Corridor 1"],
    "HOD cabin": ["Corridor 3"],

    "501": ["Corridor 1"],
    "502A": ["Corridor 1"],
    "502B": ["Corridor 1"],
    "502C": ["Corridor 1"],
    "503": ["Corridor 2"],
    "505A": ["Corridor 2"],
    "505B": ["Corridor 2"],
    "506A": ["Corridor 2"],
    "506B": ["Corridor 2"],
    "507A": ["Corridor 2"],
    "507B": ["Corridor 2"],
    "508": ["Corridor 2"],

    "511A": ["Corridor 3"],
    "511B": ["Corridor 3"],
    "512": ["Corridor 3"],
    "513A": ["Corridor 3"],
    "513B": ["Corridor 3"],
    "514": ["Corridor 3"],
    "515": ["Corridor 3"],
    "516A": ["Corridor 3"],
    "516B": ["Corridor 3"],
    "517": ["Corridor 3"],
    "518": ["Corridor 3"],
    "519": ["Corridor 3"],
    "520": ["Corridor 3"],

    "521": ["Corridor 4", "516.Stairs"],
    "522": ["Corridor 4"],
    "523": ["Corridor 4"],
    "524": ["Corridor 4"],
    "525": ["Corridor 4"],
    "526": ["Corridor 4"],
    "527": ["Corridor 4"]
}
